{
  "annotations": {
    "list": [
      {
        "builtIn": 1,
        "datasource": "-- Grafana --",
        "enable": true,
        "hide": true,
        "iconColor": "rgba(0, 211, 255, 1)",
        "name": "Annotations & Alerts",
        "type": "dashboard"
      }
    ]
  },
  "editable": true,
  "gnetId": null,
  "graphTooltip": 0,
  "id": null,
  "links": [],
  "panels": [
    {
      "datasource": "Prometheus",
      "fieldConfig": {
        "defaults": {
          "color": {
            "mode": "palette-classic"
          },
          "custom": {
            "axisLabel": "",
            "axisPlacement": "auto",
            "barAlignment": 0,
            "drawStyle": "line",
            "fillOpacity": 10,
            "gradientMode": "none",
            "hideFrom": {
              "tooltip": false,
              "viz": false,
              "legend": false
            },
            "lineInterpolation": "linear",
            "lineWidth": 1,
            "pointSize": 5,
            "scaleDistribution": {
              "type": "linear"
            },
            "showPoints": "never",
            "spanNulls": true
          },
          "mappings": [],
          "thresholds": {
            "mode": "absolute",
            "steps": [
              {
                "color": "green",
                "value": null
              },
              {
                "color": "red",
                "value": 80
              }
            ]
          },
          "unit": "short"
        },
        "overrides": []
      },
      "gridPos": {
        "h": 8,
        "w": 12,
        "x": 0,
        "y": 0
      },
      "id": 1,
      "options": {
        "legend": {
          "calcs": ["mean", "lastNotNull", "max"],
          "displayMode": "table",
          "placement": "bottom"
        },
        "tooltip": {
          "mode": "single"
        }
      },
      "pluginVersion": "8.0.0",
      "targets": [
        {
          "expr": "rate(http_requests_total{job=\"hypershimmy\"}[5m])",
          "interval": "",
          "legendFormat": "{{method}} {{endpoint}}",
          "refId": "A"
        }
      ],
      "title": "Request Rate (req/s)",
      "type": "timeseries"
    },
    {
      "datasource": "Prometheus",
      "fieldConfig": {
        "defaults": {
          "color": {
            "mode": "palette-classic"
          },
          "custom": {
            "axisLabel": "",
            "axisPlacement": "auto",
            "barAlignment": 0,
            "drawStyle": "line",
            "fillOpacity": 10,
            "gradientMode": "none",
            "hideFrom": {
              "tooltip": false,
              "viz": false,
              "legend": false
            },
            "lineInterpolation": "linear",
            "lineWidth": 1,
            "pointSize": 5,
            "scaleDistribution": {
              "type": "linear"
            },
            "showPoints": "never",
            "spanNulls": true
          },
          "mappings": [],
          "thresholds": {
            "mode": "absolute",
            "steps": [
              {
                "color": "green",
                "value": null
              },
              {
                "color": "yellow",
                "value": 100
              },
              {
                "color": "red",
                "value": 500
              }
            ]
          },
          "unit": "ms"
        },
        "overrides": []
      },
      "gridPos": {
        "h": 8,
        "w": 12,
        "x": 12,
        "y": 0
      },
      "id": 2,
      "options": {
        "legend": {
          "calcs": ["mean", "p95", "p99"],
          "displayMode": "table",
          "placement": "bottom"
        },
        "tooltip": {
          "mode": "single"
        }
      },
      "pluginVersion": "8.0.0",
      "targets": [
        {
          "expr": "histogram_quantile(0.50, rate(http_request_duration_milliseconds_bucket{job=\"hypershimmy\"}[5m]))",
          "interval": "",
          "legendFormat": "P50",
          "refId": "A"
        },
        {
          "expr": "histogram_quantile(0.95, rate(http_request_duration_milliseconds_bucket{job=\"hypershimmy\"}[5m]))",
          "interval": "",
          "legendFormat": "P95",
          "refId": "B"
        },
        {
          "expr": "histogram_quantile(0.99, rate(http_request_duration_milliseconds_bucket{job=\"hypershimmy\"}[5m]))",
          "interval": "",
          "legendFormat": "P99",
          "refId": "C"
        }
      ],
      "title": "Response Time (ms)",
      "type": "timeseries"
    },
    {
      "datasource": "Prometheus",
      "fieldConfig": {
        "defaults": {
          "color": {
            "mode": "thresholds"
          },
          "mappings": [],
          "thresholds": {
            "mode": "absolute",
            "steps": [
              {
                "color": "red",
                "value": null
              },
              {
                "color": "yellow",
                "value": 95
              },
              {
                "color": "green",
                "value": 99
              }
            ]
          },
          "unit": "percent"
        },
        "overrides": []
      },
      "gridPos": {
        "h": 4,
        "w": 4,
        "x": 0,
        "y": 8
      },
      "id": 3,
      "options": {
        "orientation": "auto",
        "reduceOptions": {
          "values": false,
          "calcs": ["lastNotNull"],
          "fields": ""
        },
        "showThresholdLabels": false,
        "showThresholdMarkers": true,
        "text": {}
      },
      "pluginVersion": "8.0.0",
      "targets": [
        {
          "expr": "(sum(rate(http_requests_total{job=\"hypershimmy\",status=~\"2..\"}[5m])) / sum(rate(http_requests_total{job=\"hypershimmy\"}[5m]))) * 100",
          "interval": "",
          "legendFormat": "",
          "refId": "A"
        }
      ],
      "title": "Success Rate",
      "type": "gauge"
    },
    {
      "datasource": "Prometheus",
      "fieldConfig": {
        "defaults": {
          "color": {
            "mode": "thresholds"
          },
          "mappings": [],
          "thresholds": {
            "mode": "absolute",
            "steps": [
              {
                "color": "green",
                "value": null
              },
              {
                "color": "yellow",
                "value": 1
              },
              {
                "color": "red",
                "value": 5
              }
            ]
          },
          "unit": "percent"
        },
        "overrides": []
      },
      "gridPos": {
        "h": 4,
        "w": 4,
        "x": 4,
        "y": 8
      },
      "id": 4,
      "options": {
        "orientation": "auto",
        "reduceOptions": {
          "values": false,
          "calcs": ["lastNotNull"],
          "fields": ""
        },
        "showThresholdLabels": false,
        "showThresholdMarkers": true,
        "text": {}
      },
      "pluginVersion": "8.0.0",
      "targets": [
        {
          "expr": "(sum(rate(http_requests_total{job=\"hypershimmy\",status=~\"5..\"}[5m])) / sum(rate(http_requests_total{job=\"hypershimmy\"}[5m]))) * 100",
          "interval": "",
          "legendFormat": "",
          "refId": "A"
        }
      ],
      "title": "Error Rate",
      "type": "gauge"
    },
    {
      "datasource": "Prometheus",
      "fieldConfig": {
        "defaults": {
          "color": {
            "mode": "thresholds"
          },
          "mappings": [],
          "thresholds": {
            "mode": "absolute",
            "steps": [
              {
                "color": "green",
                "value": null
              },
              {
                "color": "yellow",
                "value": 70
              },
              {
                "color": "red",
                "value": 90
              }
            ]
          },
          "unit": "percent"
        },
        "overrides": []
      },
      "gridPos": {
        "h": 4,
        "w": 4,
        "x": 8,
        "y": 8
      },
      "id": 5,
      "options": {
        "orientation": "auto",
        "reduceOptions": {
          "values": false,
          "calcs": ["lastNotNull"],
          "fields": ""
        },
        "showThresholdLabels": false,
        "showThresholdMarkers": true,
        "text": {}
      },
      "pluginVersion": "8.0.0",
      "targets": [
        {
          "expr": "100 - (avg by (instance) (irate(node_cpu_seconds_total{job=\"node\",mode=\"idle\"}[5m])) * 100)",
          "interval": "",
          "legendFormat": "",
          "refId": "A"
        }
      ],
      "title": "CPU Usage",
      "type": "gauge"
    },
    {
      "datasource": "Prometheus",
      "fieldConfig": {
        "defaults": {
          "color": {
            "mode": "thresholds"
          },
          "mappings": [],
          "thresholds": {
            "mode": "absolute",
            "steps": [
              {
                "color": "green",
                "value": null
              },
              {
                "color": "yellow",
                "value": 70
              },
              {
                "color": "red",
                "value": 90
              }
            ]
          },
          "unit": "percent"
        },
        "overrides": []
      },
      "gridPos": {
        "h": 4,
        "w": 4,
        "x": 12,
        "y": 8
      },
      "id": 6,
      "options": {
        "orientation": "auto",
        "reduceOptions": {
          "values": false,
          "calcs": ["lastNotNull"],
          "fields": ""
        },
        "showThresholdLabels": false,
        "showThresholdMarkers": true,
        "text": {}
      },
      "pluginVersion": "8.0.0",
      "targets": [
        {
          "expr": "(1 - (node_memory_MemAvailable_bytes{job=\"node\"} / node_memory_MemTotal_bytes{job=\"node\"})) * 100",
          "interval": "",
          "legendFormat": "",
          "refId": "A"
        }
      ],
      "title": "Memory Usage",
      "type": "gauge"
    },
    {
      "datasource": "Prometheus",
      "fieldConfig": {
        "defaults": {
          "color": {
            "mode": "thresholds"
          },
          "mappings": [],
          "thresholds": {
            "mode": "absolute",
            "steps": [
              {
                "color": "green",
                "value": null
              }
            ]
          },
          "unit": "short"
        },
        "overrides": []
      },
      "gridPos": {
        "h": 4,
        "w": 4,
        "x": 16,
        "y": 8
      },
      "id": 7,
      "options": {
        "colorMode": "value",
        "graphMode": "area",
        "justifyMode": "auto",
        "orientation": "auto",
        "reduceOptions": {
          "values": false,
          "calcs": ["lastNotNull"],
          "fields": ""
        },
        "text": {},
        "textMode": "auto"
      },
      "pluginVersion": "8.0.0",
      "targets": [
        {
          "expr": "sum(up{job=\"hypershimmy\"})",
          "interval": "",
          "legendFormat": "",
          "refId": "A"
        }
      ],
      "title": "Active Instances",
      "type": "stat"
    },
    {
      "datasource": "Prometheus",
      "fieldConfig": {
        "defaults": {
          "color": {
            "mode": "palette-classic"
          },
          "custom": {
            "axisLabel": "",
            "axisPlacement": "auto",
            "barAlignment": 0,
            "drawStyle": "line",
            "fillOpacity": 10,
            "gradientMode": "none",
            "hideFrom": {
              "tooltip": false,
              "viz": false,
              "legend": false
            },
            "lineInterpolation": "linear",
            "lineWidth": 1,
            "pointSize": 5,
            "scaleDistribution": {
              "type": "linear"
            },
            "showPoints": "never",
            "spanNulls": true
          },
          "mappings": [],
          "thresholds": {
            "mode": "absolute",
            "steps": [
              {
                "color": "green",
                "value": null
              }
            ]
          },
          "unit": "short"
        },
        "overrides": []
      },
      "gridPos": {
        "h": 8,
        "w": 12,
        "x": 0,
        "y": 12
      },
      "id": 8,
      "options": {
        "legend": {
          "calcs": ["mean", "lastNotNull"],
          "displayMode": "table",
          "placement": "bottom"
        },
        "tooltip": {
          "mode": "single"
        }
      },
      "pluginVersion": "8.0.0",
      "targets": [
        {
          "expr": "rate(http_requests_total{job=\"hypershimmy\",status=~\"5..\"}[5m])",
          "interval": "",
          "legendFormat": "{{status}} - {{endpoint}}",
          "refId": "A"
        }
      ],
      "title": "Error Rate by Endpoint",
      "type": "timeseries"
    },
    {
      "datasource": "Prometheus",
      "fieldConfig": {
        "defaults": {
          "color": {
            "mode": "palette-classic"
          },
          "custom": {
            "axisLabel": "",
            "axisPlacement": "auto",
            "barAlignment": 0,
            "drawStyle": "line",
            "fillOpacity": 10,
            "gradientMode": "none",
            "hideFrom": {
              "tooltip": false,
              "viz": false,
              "legend": false
            },
            "lineInterpolation": "linear",
            "lineWidth": 1,
            "pointSize": 5,
            "scaleDistribution": {
              "type": "linear"
            },
            "showPoints": "never",
            "spanNulls": true
          },
          "mappings": [],
          "thresholds": {
            "mode": "absolute",
            "steps": [
              {
                "color": "green",
                "value": null
              }
            ]
          },
          "unit": "short"
        },
        "overrides": []
      },
      "gridPos": {
        "h": 8,
        "w": 12,
        "x": 12,
        "y": 12
      },
      "id": 9,
      "options": {
        "legend": {
          "calcs": ["mean", "lastNotNull"],
          "displayMode": "table",
          "placement": "bottom"
        },
        "tooltip": {
          "mode": "single"
        }
      },
      "pluginVersion": "8.0.0",
      "targets": [
        {
          "expr": "sum by (endpoint) (rate(http_requests_total{job=\"hypershimmy\"}[5m]))",
          "interval": "",
          "legendFormat": "{{endpoint}}",
          "refId": "A"
        }
      ],
      "title": "Requests by Endpoint",
      "type": "timeseries"
    },
    {
      "datasource": "Prometheus",
      "fieldConfig": {
        "defaults": {
          "color": {
            "mode": "palette-classic"
          },
          "custom": {
            "axisLabel": "",
            "axisPlacement": "auto",
            "barAlignment": 0,
            "drawStyle": "line",
            "fillOpacity": 10,
            "gradientMode": "none",
            "hideFrom": {
              "tooltip": false,
              "viz": false,
              "legend": false
            },
            "lineInterpolation": "linear",
            "lineWidth": 1,
            "pointSize": 5,
            "scaleDistribution": {
              "type": "linear"
            },
            "showPoints": "never",
            "spanNulls": true
          },
          "mappings": [],
          "thresholds": {
            "mode": "absolute",
            "steps": [
              {
                "color": "green",
                "value": null
              }
            ]
          },
          "unit": "bytes"
        },
        "overrides": []
      },
      "gridPos": {
        "h": 8,
        "w": 12,
        "x": 0,
        "y": 20
      },
      "id": 10,
      "options": {
        "legend": {
          "calcs": ["mean", "lastNotNull"],
          "displayMode": "table",
          "placement": "bottom"
        },
        "tooltip": {
          "mode": "single"
        }
      },
      "pluginVersion": "8.0.0",
      "targets": [
        {
          "expr": "process_resident_memory_bytes{job=\"hypershimmy\"}",
          "interval": "",
          "legendFormat": "RSS",
          "refId": "A"
        },
        {
          "expr": "process_virtual_memory_bytes{job=\"hypershimmy\"}",
          "interval": "",
          "legendFormat": "Virtual",
          "refId": "B"
        }
      ],
      "title": "Memory Usage Details",
      "type": "timeseries"
    },
    {
      "datasource": "Prometheus",
      "fieldConfig": {
        "defaults": {
          "color": {
            "mode": "palette-classic"
          },
          "custom": {
            "axisLabel": "",
            "axisPlacement": "auto",
            "barAlignment": 0,
            "drawStyle": "line",
            "fillOpacity": 10,
            "gradientMode": "none",
            "hideFrom": {
              "tooltip": false,
              "viz": false,
              "legend": false
            },
            "lineInterpolation": "linear",
            "lineWidth": 1,
            "pointSize": 5,
            "scaleDistribution": {
              "type": "linear"
            },
            "showPoints": "never",
            "spanNulls": true
          },
          "mappings": [],
          "thresholds": {
            "mode": "absolute",
            "steps": [
              {
                "color": "green",
                "value": null
              }
            ]
          },
          "unit": "ms"
        },
        "overrides": []
      },
      "gridPos": {
        "h": 8,
        "w": 12,
        "x": 12,
        "y": 20
      },
      "id": 11,
      "options": {
        "legend": {
          "calcs": ["mean", "lastNotNull"],
          "displayMode": "table",
          "placement": "bottom"
        },
        "tooltip": {
          "mode": "single"
        }
      },
      "pluginVersion": "8.0.0",
      "targets": [
        {
          "expr": "rate(database_query_duration_milliseconds_sum{job=\"hypershimmy\"}[5m]) / rate(database_query_duration_milliseconds_count{job=\"hypershimmy\"}[5m])",
          "interval": "",
          "legendFormat": "{{query_type}}",
          "refId": "A"
        }
      ],
      "title": "Database Query Duration",
      "type": "timeseries"
    }
  ],
  "schemaVersion": 27,
  "style": "dark",
  "tags": ["hypershimmy", "production"],
  "templating": {
    "list": []
  },
  "time": {
    "from": "now-6h",
    "to": "now"
  },
  "timepicker": {},
  "timezone": "",
  "title": "HyperShimmy Production Dashboard",
  "uid": "hypershimmy-prod",
  "version": 1
}
